edges_analysis/__init__.py
edges_analysis/_data_retrieval.py
edges_analysis/cli.py
edges_analysis/config.py
edges_analysis/const.py
edges_analysis/analysis/__init__.py
edges_analysis/analysis/averaging.py
edges_analysis/analysis/beams.py
edges_analysis/analysis/calibrate.py
edges_analysis/analysis/coordinates.py
edges_analysis/analysis/filters.py
edges_analysis/analysis/levels.py
edges_analysis/analysis/loss.py
edges_analysis/analysis/plots.py
edges_analysis/analysis/s11.py
edges_analysis/analysis/sky_models.py
edges_analysis/analysis/tools.py
edges_analysis/analysis/data/Lowband_30mx30m_Haslam_2p5_20minlst_50_100.npy
edges_analysis/analysis/data/__init__.py
edges_analysis/analysis/data/beams/high/default.txt
edges_analysis/analysis/data/beams/low/45deg.txt
edges_analysis/analysis/data/beams/low/default.txt
edges_analysis/analysis/data/beams/mid/default.txt
edges_analysis/analysis/data/loss/low/ground.txt
edges_analysis/analysis/data/loss/low/ground_45deg.txt
edges_analysis/analysis/data/loss/mid/antenna.txt
edges_analysis/analysis/data/loss/mid/ground.txt
edges_analysis/simulation/__init__.py
edges_analysis/simulation/plots.py
edges_analysis-4.1.3.dist-info/AUTHORS.rst
edges_analysis-4.1.3.dist-info/LICENSE.txt
edges_analysis-4.1.3.dist-info/METADATA
edges_analysis-4.1.3.dist-info/WHEEL
edges_analysis-4.1.3.dist-info/entry_points.txt
edges_analysis-4.1.3.dist-info/top_level.txt
edges_analysis-4.1.3.dist-info/RECORD
